buildmgr/__init__.py
buildmgr/core.py
buildmgr/py.typed
buildmgr-0.1.1.dist-info/licenses/LICENSE
buildmgr-0.1.1.dist-info/METADATA
buildmgr-0.1.1.dist-info/WHEEL
buildmgr-0.1.1.dist-info/top_level.txt
buildmgr-0.1.1.dist-info/RECORD
