Metadata-Version: 2.4
Name: buildmgr
Version: 0.1.1
Summary: A simple Python-based build system
Author-email: Noah Blair <noahjblair@outlook.com>
Requires-Python: >=3.9
License-File: LICENSE
Dynamic: license-file
